simulation/__init__.py
simulation/run_simulation.py
simulation/.idea/.gitignore
simulation/.idea/misc.xml
simulation/.idea/modules.xml
simulation/.idea/simulation.iml
simulation/.idea/vcs.xml
simulation/.idea/inspectionProfiles/profiles_settings.xml
simulation/arrays/__init__.py
simulation/arrays/base_array.py
simulation/arrays/basic_array.py
simulation/battery/__init__.py
simulation/battery/base_battery.py
simulation/battery/basic_battery.py
simulation/cache/__init__.py
simulation/cache/route/__init__.py
simulation/cache/route/route_data.npz
simulation/cache/route/route_data_FSGP.npz
simulation/cache/weather/__init__.py
simulation/cache/weather/weather_data.npz
simulation/common/__init__.py
simulation/common/car.py
simulation/common/constants.py
simulation/common/consumer.py
simulation/common/equations.py
simulation/common/exceptions.py
simulation/common/helpers.py
simulation/common/producer.py
simulation/common/race.py
simulation/common/storage.py
simulation/config/BrightSide.json
simulation/config/DayBreak.json
simulation/config/__init__.py
simulation/config/initial_conditions_ASC.json
simulation/config/initial_conditions_FSGP.json
simulation/config/settings_ASC.json
simulation/config/settings_FSGP.json
simulation/data/__init__.py
simulation/data/logo.png
simulation/data/images/a3069742-3dec-4a33-ad2c-645f5f67ce6b.png
simulation/data/images/coordinates.json
simulation/environment/GIS.py
simulation/environment/SolarCalculations.py
simulation/environment/WeatherForecasts.py
simulation/environment/__init__.py
simulation/library/COMPILING_HOWTO.md
simulation/library/__init__.py
simulation/library/libraries.py
simulation/library/binaries/__init__.py
simulation/library/binaries/darwin_arm64/main.h
simulation/library/binaries/darwin_arm64/main.so
simulation/library/binaries/darwin_arm64/perlin_noise.h
simulation/library/binaries/darwin_arm64/perlin_noise.so
simulation/library/binaries/linux_amd64/main.h
simulation/library/binaries/linux_amd64/main.so
UBC_Solar_Simulation-0.7.2.dist-info/LICENSE
UBC_Solar_Simulation-0.7.2.dist-info/METADATA
UBC_Solar_Simulation-0.7.2.dist-info/WHEEL
UBC_Solar_Simulation-0.7.2.dist-info/entry_points.txt
UBC_Solar_Simulation-0.7.2.dist-info/top_level.txt
UBC_Solar_Simulation-0.7.2.dist-info/RECORD
