Metadata-Version: 2.1
Name: UBC-Solar-Simulation
Version: 0.7.2
Summary: UBC Solar's Simulation Environment
Author: Fisher Xue, Mihir Nimgade, Chris Chang, David Widjaja, Justin Hua, Ilya Veksler, Renu Rajamagesh, Ritchie Xia, Erik Langille, Chris Aung, Nicolas Ric, Ishaan Trivedi, Jason Liang, Felix Toft, Mack Wilson, Jonah Lee, Tamzeed Quazi, Joshua Riefman
Author-email: UBC Solar <software@ubcsolar.com>
Maintainer: Renu Rajamagmesh, Felix Toft, Mack Wilson, Jonah Lee, Tamzeed Quazi
Maintainer-email: UBC Solar <software@ubcsolar.com>, Joshua Riefman <joshuariefman@gmail.com>
License: MIT License
Project-URL: Homepage, https://ubcsolar.com
Project-URL: Repository, https://github.com/UBC-Solar/Simulation
Project-URL: Documentation, https://wiki.ubcsolar.com
Keywords: car,simulation,solar
Classifier: Programming Language :: Python :: 3
Classifier: Natural Language :: English
Classifier: Topic :: Scientific/Engineering :: Physics
Requires-Python: >=3.8
License-File: LICENSE
Requires-Dist: bayesian-optimization ==1.4.3
Requires-Dist: bokeh ==2.3.3
Requires-Dist: matplotlib
Requires-Dist: numpy
Requires-Dist: pandas
Requires-Dist: Pillow ==9.4.0
Requires-Dist: plotly ==5.6.0
Requires-Dist: polyline ==1.4.0
Requires-Dist: pytest ==7.1.1
Requires-Dist: python-dotenv ==1.0.0
Requires-Dist: pytz ==2021.3
Requires-Dist: requests ==2.26.0
Requires-Dist: scikit-learn ==1.2.2
Requires-Dist: setuptools ==61.2.0
Requires-Dist: timezonefinder ==6.0.1
Requires-Dist: tqdm ==4.64.0
Requires-Dist: strenum ==0.4.15
Requires-Dist: perlin-noise ==1.12
Requires-Dist: cffi ==1.15.1
